{
  "category": "residential",
  "status": "completed",
  "location": "DHA Phase 7, Lahore",
  "startDate": "2024-07-06",
  "isFeatured": true,
  "coverImage": "https://res.cloudinary.com/dsm8ysq8w/image/upload/v1774912965/5d0ee464-6d8e-45aa-b4cd-6845c8a72304_x8sua0.jpg",
  "images": [],
  "description": "The modern 1 kanal house in DHA Phase 7 was designed to reflect elegance, functionality, and premium living standards. Real Enterprises developed this project with a contemporary architectural style, combining clean lines, spacious interiors, and high-end finishes throughout the home.\n\nThe residence features large bedrooms with attached bathrooms, a modern kitchen, open living and dining spaces, stylish ceilings, and premium flooring. Floor-to-ceiling windows were incorporated to maximize natural light and create a bright, open atmosphere across the house.\n\nSpecial focus was placed on exterior elevation, landscaping, lighting, and smart use of space to ensure the property delivers both luxury and practicality. Every detail, from structural work to final finishing, was completed with precision and attention to quality.\n\nThis house stands as another example of Real Enterprises’ expertise in delivering modern homes in premium communities like DHA Phase 7"
}
